{
  "doc_key": "brand_guideline",
  "doc_title": "Brand Guideline",
  "doc_kind": "configuration",
  "status": "draft",
  "module_id": "brand_management",
  "submodule_id": "brand_controls",
  "app_id": "marketing",
  "base_action_profile": "base_record_actions",
  "doc_archetype": "configuration",
  "classification": {
    "archetype": "configuration",
    "bundle": "operations",
    "doc_kind": "configuration"
  },
  "planning_source": {
    "type": "reference_doc_generation_manifest",
    "bundle": "operations",
    "app": "marketing",
    "module": "brand_management",
    "submodule": "brand_controls",
    "reference_doc_id": "brand_guideline",
    "evidence_gaps": [
      "control taxonomy",
      "mandatory-acknowledgment handling"
    ]
  },
  "ui": {
    "icon_key": "settings",
    "accent": "#5c677d",
    "logo_image": null,
    "cover_image": null,
    "preferred_views": [
      "list",
      "table",
      "detail",
      "report"
    ],
    "default_density": "comfortable"
  },
  "dashboard": {
    "version": 1,
    "surface": "doc",
    "hero": {
      "variant": "summary_strip",
      "show_breadcrumb": true,
      "show_title": true
    },
    "navigation": {
      "primary_children": "records",
      "flatten_submodules_in_ui": false,
      "views": [
        "list",
        "table",
        "detail",
        "report"
      ]
    },
    "blocks": [
      {
        "id": "kpis",
        "type": "kpi_cards",
        "title": "Brand Guideline KPIs",
        "data_source": {
          "kind": "db",
          "entity_scope": "doc",
          "entity_id": "brand_guideline",
          "metric_family": "overview"
        }
      },
      {
        "id": "summaries",
        "type": "summary_cards",
        "title": "Brand Guideline summaries",
        "data_source": {
          "kind": "db",
          "entity_scope": "doc",
          "entity_id": "brand_guideline",
          "metric_family": "summary"
        }
      },
      {
        "id": "charts",
        "type": "chart_group",
        "title": "Brand Guideline charts",
        "data_source": {
          "kind": "db",
          "entity_scope": "doc",
          "entity_id": "brand_guideline",
          "metric_family": "trend"
        }
      },
      {
        "id": "reports",
        "type": "report_links",
        "title": "Brand Guideline reports",
        "data_source": {
          "kind": "db",
          "entity_scope": "doc",
          "entity_id": "brand_guideline",
          "metric_family": "reporting"
        }
      },
      {
        "id": "records",
        "type": "record_table",
        "title": "Brand Guideline records",
        "data_source": {
          "kind": "db",
          "entity_scope": "doc",
          "entity_id": "brand_guideline",
          "metric_family": "records"
        }
      }
    ]
  },
  "reporting": {
    "supports_kpis": true,
    "supports_summaries": true,
    "supports_charts": true,
    "supports_reports": true,
    "default_time_grain": "month",
    "default_comparison": "previous_period",
    "default_currency_mode": "base_currency",
    "metric_sources": [
      {
        "id": "overview",
        "kind": "db",
        "entity_scope": "doc",
        "entity_id": "brand_guideline",
        "metric_family": "overview"
      },
      {
        "id": "summary",
        "kind": "db",
        "entity_scope": "doc",
        "entity_id": "brand_guideline",
        "metric_family": "summary"
      },
      {
        "id": "trend",
        "kind": "db",
        "entity_scope": "doc",
        "entity_id": "brand_guideline",
        "metric_family": "trend"
      },
      {
        "id": "reporting",
        "kind": "db",
        "entity_scope": "doc",
        "entity_id": "brand_guideline",
        "metric_family": "reporting"
      }
    ],
    "report_registry": [
      {
        "id": "overview_report",
        "label": "Brand Guideline Overview",
        "report_type": "dashboard_summary",
        "surface": "doc"
      },
      {
        "id": "trend_report",
        "label": "Brand Guideline Trends",
        "report_type": "trend_analysis",
        "surface": "doc"
      },
      {
        "id": "summary_report",
        "label": "Brand Guideline Summary",
        "report_type": "summary_report",
        "surface": "doc"
      },
      {
        "id": "detail_report",
        "label": "Brand Guideline Detail",
        "report_type": "detail_report",
        "surface": "doc"
      }
    ],
    "supports_outputs": false,
    "supports_print_formats": true,
    "default_views": [
      "summary",
      "trend",
      "report_table"
    ],
    "chart_library": {
      "renderer": "recharts",
      "recommended_package": "recharts",
      "source": "https://recharts.org/en-US"
    },
    "chart_registry": [
      {
        "id": "brand_guideline_trend_line",
        "label": "Brand Guideline trend",
        "chart_type": "line",
        "series_role": "time_series",
        "metric_family": "trend",
        "x_field": "period",
        "y_field": "value"
      },
      {
        "id": "brand_guideline_volume_column",
        "label": "Brand Guideline volume",
        "chart_type": "column",
        "series_role": "comparison",
        "metric_family": "summary",
        "x_field": "category",
        "y_field": "count"
      },
      {
        "id": "brand_guideline_distribution_donut",
        "label": "Brand Guideline distribution",
        "chart_type": "donut",
        "series_role": "distribution",
        "metric_family": "summary",
        "segment_field": "category",
        "value_field": "value"
      }
    ]
  },
  "flow": {
    "related_docs": [
      "brand_asset",
      "brand_campaign_brief"
    ],
    "upstream_docs": [
      "brand_asset",
      "brand_campaign_brief"
    ],
    "downstream_docs": [],
    "borrowed_fields": [],
    "emits_records": [],
    "downstream_effects": [
      "supports campaigns, product marketing, and external communications"
    ],
    "actors": [
      "brand owner",
      "designer",
      "reviewer"
    ],
    "handoff_targets": [
      "brand_asset",
      "brand_campaign_brief"
    ],
    "graph_edges": [
      {
        "source_doc": "brand_guideline",
        "target_doc": "brand_asset",
        "relation": "references"
      },
      {
        "source_doc": "brand_guideline",
        "target_doc": "brand_campaign_brief",
        "relation": "references"
      }
    ]
  },
  "contract_version": 1
}
